qti_package_maker/__init__.py
qti_package_maker/package_interface.py
qti_package_maker/assessment_items/item_bank.py
qti_package_maker/assessment_items/item_types.py
qti_package_maker/assessment_items/validator.py
qti_package_maker/common/__init__.py
qti_package_maker/common/anti_cheat.py
qti_package_maker/common/color_wheel.py
qti_package_maker/common/franken_bptools.py
qti_package_maker/common/qti_manifest.py
qti_package_maker/common/string_functions.py
qti_package_maker/common/yaml_tools.py
qti_package_maker/data/all_short_words.txt
qti_package_maker/engines/__init__.py
qti_package_maker/engines/base_engine.py
qti_package_maker/engines/engine_registration.py
qti_package_maker/engines/bbq_text_upload/__init__.py
qti_package_maker/engines/bbq_text_upload/engine_class.py
qti_package_maker/engines/bbq_text_upload/read_package.py
qti_package_maker/engines/bbq_text_upload/write_item.py
qti_package_maker/engines/blackboard_qti_v2_1/__init__.py
qti_package_maker/engines/blackboard_qti_v2_1/assessment_meta.py
qti_package_maker/engines/blackboard_qti_v2_1/engine_class.py
qti_package_maker/engines/blackboard_qti_v2_1/item_xml_helpers.py
qti_package_maker/engines/blackboard_qti_v2_1/write_item.py
qti_package_maker/engines/canvas_qti_v1_2/__init__.py
qti_package_maker/engines/canvas_qti_v1_2/assessment_meta.py
qti_package_maker/engines/canvas_qti_v1_2/engine_class.py
qti_package_maker/engines/canvas_qti_v1_2/item_xml_helpers.py
qti_package_maker/engines/canvas_qti_v1_2/write_item.py
qti_package_maker/engines/html_selftest/__init__.py
qti_package_maker/engines/html_selftest/add_FIB.py
qti_package_maker/engines/html_selftest/add_MA.py
qti_package_maker/engines/html_selftest/add_MATCH.py
qti_package_maker/engines/html_selftest/add_MC.py
qti_package_maker/engines/html_selftest/add_MULTI_FIB.py
qti_package_maker/engines/html_selftest/add_NUM.py
qti_package_maker/engines/html_selftest/add_ORDER.py
qti_package_maker/engines/html_selftest/engine_class.py
qti_package_maker-0.8.6.dist-info/METADATA
qti_package_maker-0.8.6.dist-info/WHEEL
qti_package_maker-0.8.6.dist-info/top_level.txt
qti_package_maker-0.8.6.dist-info/RECORD
