Metadata-Version: 2.4
Name: qti_package_maker
Version: 0.8.6
Summary: A package to create, manage, and convert QTI packages for quizzes and assessments in Canvas, Blackboard, Moodle, and LibreTexts ADAPT.
Author: Dr. Neil Voss
Project-URL: Homepage, https://biologyproblems.org
Project-URL: Repository, https://github.com/vosslab/qti_package_maker
Project-URL: PyPI, https://pypi.org/project/qti-package-maker/
Keywords: QTI,quiz,assessment,test package,Canvas,Blackboard,Moodle,LibreTexts ADAPT,e-learning,LMS,question bank,quiz converter,online learning,exam generator,QTI exporter,IMS Question and Test Interoperability specification,Question and Test Interoperability,XML,QTI v2.1,QTI v1.2
Classifier: Development Status :: 4 - Beta
Classifier: Intended Audience :: Education
Classifier: Intended Audience :: Developers
Classifier: License :: OSI Approved :: GNU General Public License v3 (GPLv3)
Classifier: Programming Language :: Python :: 3
Classifier: Topic :: Education :: Testing
Classifier: Topic :: Software Development :: Libraries :: Python Modules
Classifier: Operating System :: OS Independent
Requires-Python: >=3.9
Requires-Dist: crcmod
Requires-Dist: lxml
Requires-Dist: num2words
Requires-Dist: pyyaml
Requires-Dist: tabulate
